DFRobot/DFR_ADS1115.py
DFRobot/DFR_EC.py
DFRobot/DFR_PH.py
DFRobot/__init__.py
DFRobot_EC_PH_ADC-0.1.1.dist-info/LICENSE
DFRobot_EC_PH_ADC-0.1.1.dist-info/METADATA
DFRobot_EC_PH_ADC-0.1.1.dist-info/WHEEL
DFRobot_EC_PH_ADC-0.1.1.dist-info/top_level.txt
DFRobot_EC_PH_ADC-0.1.1.dist-info/RECORD
