Metadata-Version: 2.1
Name: DFRobot-EC-PH-ADC
Version: 0.1.1
Summary: This package is a fork of the DFRobot_PH package, modified for python3 and packaged for pip
Home-page: https://github.com/moha7108/DFRobot_PH
Author: Mohamed Debbagh
Author-email: moha7108@protonmail.com
License: GNU LGPL-2.1
Project-URL: Bug Tracker, https://github.com/moha7108/DFRobot_PH/issues
Project-URL: Github, https://github.com/moha7108/DFRobot_PH
Keywords: Raspberry Pi,Raspi,Python,GPIO,PH,EC,DFRobot,Gravity,Sensor
Platform: UNKNOWN
Classifier: Programming Language :: Python :: 3
Classifier: License :: OSI Approved :: GNU Lesser General Public License v2 or later (LGPLv2+)
Classifier: Operating System :: POSIX :: Linux
Classifier: Development Status :: 3 - Alpha
Requires-Python: >=2
License-File: LICENSE
Requires-Dist: smbus
